core/__init__.py
core/color_cluster_cv.py
core/color_compare.py
core/color_seg.py
core/curvature.py
core/demo_color_seg.py
core/demo_trait_extract_parallel.py
core/gamma_correction.py
core/histogram_equalization.py
core/luminous_detection.py
core/marker_roi_crop.py
core/mask_skeleton.py
core/mutiple_object_segmentation.py
core/options.py
core/pipeline.py
core/results.py
core/thresholding.py
core/track_load_ori.py
core/trait_extract.py
core/trait_extract_gray.py
core/trait_extract_parallel.py
core/trait_extract_parallel_ori.py
core/utils.py
core/workflow.py
tools/__init__.py
tools/color_cluster_cv.py
tools/color_kmeans_vis.py
tools/color_seg.py
tools/curvature.py
tools/superpixel.py
tools/utils.py
tools/watershed_cv.py
smart_arabidopsis_traits-0.5.4.dist-info/LICENSE
smart_arabidopsis_traits-0.5.4.dist-info/METADATA
smart_arabidopsis_traits-0.5.4.dist-info/WHEEL
smart_arabidopsis_traits-0.5.4.dist-info/entry_points.txt
smart_arabidopsis_traits-0.5.4.dist-info/top_level.txt
smart_arabidopsis_traits-0.5.4.dist-info/RECORD
