Metadata-Version: 2.1
Name: smart-arabidopsis-traits
Version: 0.5.4
Summary: Extract geometric traits from top-view images of plants.
Home-page: https://github.com/Computational-Plant-Science/SMART
Author: Suxing Liu
Author-email: suxing.liu@uga.edu
License: BSD-3-Clause
Platform: UNKNOWN
Requires-Python: >=3.6.8
Requires-Dist: click
Requires-Dist: psutil
Requires-Dist: numba
Requires-Dist: pandas
Requires-Dist: networkx
Requires-Dist: skan
Requires-Dist: tabulate
Requires-Dist: imutils
Requires-Dist: python-magic
Requires-Dist: seaborn
Requires-Dist: openpyxl
Requires-Dist: opencv-python
Requires-Dist: matplotlib
Requires-Dist: scikit-learn
Requires-Dist: scikit-image
Requires-Dist: scikit-build
Requires-Dist: scipy
Requires-Dist: Pillow (==9.0.1)
Requires-Dist: mayavi
Requires-Dist: progressbar
Requires-Dist: moviepy
